opentool/__init__.py
opentool/version.py
opentool/runner/__init__.py
opentool/runner/base_runner.py
opentool/runner/checkpoint.py
opentool/runner/factory.py
opentool/runner/utils.py
opentool/utils/__init__.py
opentool/utils/config.py
opentool/utils/logging.py
opentool/utils/misc.py
opentool/utils/path.py
opentool-0.0.15.dist-info/DESCRIPTION.rst
opentool-0.0.15.dist-info/METADATA
opentool-0.0.15.dist-info/RECORD
opentool-0.0.15.dist-info/WHEEL
opentool-0.0.15.dist-info/metadata.json
opentool-0.0.15.dist-info/top_level.txt
